istampit_cli/__init__.py
istampit_cli/__main__.py
istampit_cli/stamp_hash.py
istampit_cli-1.0.5.dist-info/licenses/LICENSE
istampit_cli-1.0.5.dist-info/METADATA
istampit_cli-1.0.5.dist-info/WHEEL
istampit_cli-1.0.5.dist-info/entry_points.txt
istampit_cli-1.0.5.dist-info/top_level.txt
istampit_cli-1.0.5.dist-info/RECORD
