Metadata-Version: 2.4
Name: istampit-cli
Version: 1.0.5
Summary: iStampit CLI – Blockchain timestamp verification with OpenTimestamps
Author-email: "SinAI Inc." <pypi@eihdah.com>
License: MIT
Project-URL: Homepage, https://github.com/SinAi-Inc/istampit-cli
Project-URL: Documentation, https://github.com/SinAi-Inc/istampit-cli#readme
Project-URL: Source, https://github.com/SinAi-Inc/istampit-cli
Project-URL: Tracker, https://github.com/SinAi-Inc/istampit-cli/issues
Requires-Python: >=3.9
License-File: LICENSE
Requires-Dist: opentimestamps-client>=0.7.0
Dynamic: license-file
